<?xml version="1.0" encoding="UTF-8"?>
<graph xmlns="http://www.xces.org/ns/GrAF/1.0/">
    <graphHeader>
        <labelsDecl>
            <labelUsage label="Date" occurs="2"/>
            <labelUsage label="Location" occurs="2"/>
            <labelUsage label="PRN" occurs="11"/>
            <labelUsage label="Person" occurs="3"/>
            <labelUsage label="NounChunk" occurs="52"/>
        </labelsDecl>
        <annotationSpaces>
            <annotationSpace as.id="anc"/>
        </annotationSpaces>
    </graphHeader>
    <region xml:id="r1" anchors="3 7"/>
    <region xml:id="r3" anchors="10 40"/>
    <region xml:id="r6" anchors="48 58"/>
    <region xml:id="r9" anchors="61 104"/>
    <region xml:id="r11" anchors="110 121"/>
    <region xml:id="r13" anchors="122 129"/>
    <region xml:id="r15" anchors="138 152"/>
    <region xml:id="r17" anchors="178 192"/>
    <region xml:id="r19" anchors="203 215"/>
    <region xml:id="r21" anchors="218 223"/>
    <region xml:id="r23" anchors="244 252"/>
    <region xml:id="r25" anchors="254 258"/>
    <region xml:id="r28" anchors="262 280"/>
    <region xml:id="r30" anchors="285 298"/>
    <region xml:id="r32" anchors="301 304"/>
    <region xml:id="r34" anchors="308 329"/>
    <region xml:id="r36" anchors="331 360"/>
    <region xml:id="r38" anchors="367 377"/>
    <region xml:id="r40" anchors="387 396"/>
    <region xml:id="r42" anchors="404 408"/>
    <region xml:id="r44" anchors="412 416"/>
    <region xml:id="r46" anchors="417 423"/>
    <region xml:id="r48" anchors="435 447"/>
    <region xml:id="r50" anchors="450 451"/>
    <region xml:id="r53" anchors="467 479"/>
    <region xml:id="r55" anchors="490 502"/>
    <region xml:id="r57" anchors="490 492"/>
    <region xml:id="r59" anchors="504 506"/>
    <region xml:id="r62" anchors="518 524"/>
    <region xml:id="r64" anchors="528 539"/>
    <region xml:id="r66" anchors="528 531"/>
    <region xml:id="r68" anchors="555 557"/>
    <region xml:id="r71" anchors="568 604"/>
    <region xml:id="r73" anchors="607 616"/>
    <region xml:id="r76" anchors="618 624"/>
    <region xml:id="r79" anchors="629 643"/>
    <region xml:id="r81" anchors="644 645"/>
    <region xml:id="r84" anchors="657 685"/>
    <region xml:id="r86" anchors="686 687"/>
    <region xml:id="r89" anchors="701 707"/>
    <region xml:id="r91" anchors="715 716"/>
    <region xml:id="r94" anchors="730 739"/>
    <region xml:id="r96" anchors="741 746"/>
    <region xml:id="r98" anchors="774 775"/>
    <region xml:id="r101" anchors="784 795"/>
    <region xml:id="r103" anchors="807 817"/>
    <region xml:id="r105" anchors="822 835"/>
    <region xml:id="r108" anchors="837 838"/>
    <region xml:id="r111" anchors="859 875"/>
    <region xml:id="r113" anchors="878 888"/>
    <region xml:id="r116" anchors="890 903"/>
    <region xml:id="r119" anchors="913 930"/>
    <region xml:id="r121" anchors="934 956"/>
    <region xml:id="r123" anchors="968 1004"/>
    <node xml:id="n0">
        <link targets="r1"/>
    </node>
    <a xml:id="a-225106" label="NounChunk" ref="n0" as="anc">
        <fs>
            <f name="id" value="217"/>
        </fs>
    </a>
    <node xml:id="n1">
        <link targets="r3"/>
    </node>
    <a xml:id="a-225107" label="NounChunk" ref="n1" as="anc">
        <fs>
            <f name="id" value="219"/>
        </fs>
    </a>
    <a xml:id="a-225108" label="Date" ref="n1" as="anc">
        <fs>
            <f name="kind" value="dateTime"/>
            <f name="id" value="33219"/>
        </fs>
    </a>
    <node xml:id="n10">
        <link targets="r23"/>
    </node>
    <a xml:id="a-225118" label="NounChunk" ref="n10" as="anc">
        <fs>
            <f name="id" value="228"/>
        </fs>
    </a>
    <node xml:id="n11">
        <link targets="r25"/>
    </node>
    <a xml:id="a-225119" label="NounChunk" ref="n11" as="anc">
        <fs>
            <f name="id" value="31"/>
        </fs>
    </a>
    <a xml:id="a-225120" label="PRN" ref="n11" as="anc">
        <fs>
            <f name="person" value="third"/>
            <f name="case" value="nominative"/>
            <f name="string" value="This"/>
            <f name="id" value="302"/>
            <f name="matches" value="[]"/>
            <f name="type" value="anaphoric"/>
            <f name="cls" value="Thing"/>
            <f name="number" value="singular"/>
        </fs>
    </a>
    <node xml:id="n12">
        <link targets="r28"/>
    </node>
    <a xml:id="a-225121" label="NounChunk" ref="n12" as="anc">
        <fs>
            <f name="id" value="230"/>
        </fs>
    </a>
    <node xml:id="n13">
        <link targets="r30"/>
    </node>
    <a xml:id="a-225122" label="NounChunk" ref="n13" as="anc">
        <fs>
            <f name="id" value="231"/>
        </fs>
    </a>
    <node xml:id="n14">
        <link targets="r32"/>
    </node>
    <a xml:id="a-225123" label="NounChunk" ref="n14" as="anc">
        <fs>
            <f name="id" value="232"/>
        </fs>
    </a>
    <node xml:id="n15">
        <link targets="r34"/>
    </node>
    <a xml:id="a-225124" label="NounChunk" ref="n15" as="anc">
        <fs>
            <f name="id" value="233"/>
        </fs>
    </a>
    <node xml:id="n16">
        <link targets="r36"/>
    </node>
    <a xml:id="a-225125" label="NounChunk" ref="n16" as="anc">
        <fs>
            <f name="id" value="234"/>
        </fs>
    </a>
    <node xml:id="n17">
        <link targets="r38"/>
    </node>
    <a xml:id="a-225126" label="NounChunk" ref="n17" as="anc">
        <fs>
            <f name="id" value="235"/>
        </fs>
    </a>
    <node xml:id="n18">
        <link targets="r40"/>
    </node>
    <a xml:id="a-225127" label="NounChunk" ref="n18" as="anc">
        <fs>
            <f name="id" value="236"/>
        </fs>
    </a>
    <node xml:id="n19">
        <link targets="r42"/>
    </node>
    <a xml:id="a-225128" label="NounChunk" ref="n19" as="anc">
        <fs>
            <f name="id" value="237"/>
        </fs>
    </a>
    <node xml:id="n2">
        <link targets="r6"/>
    </node>
    <a xml:id="a-225109" label="Person" ref="n2" as="anc">
        <fs>
            <f name="gender" value="male"/>
            <f name="isFirst" value="true"/>
            <f name="id" value="272"/>
        </fs>
    </a>
    <a xml:id="a-225110" label="NounChunk" ref="n2" as="anc">
        <fs>
            <f name="id" value="30"/>
        </fs>
    </a>
    <node xml:id="n20">
        <link targets="r44"/>
    </node>
    <a xml:id="a-225129" label="NounChunk" ref="n20" as="anc">
        <fs>
            <f name="id" value="238"/>
        </fs>
    </a>
    <node xml:id="n21">
        <link targets="r46"/>
    </node>
    <a xml:id="a-225130" label="NounChunk" ref="n21" as="anc">
        <fs>
            <f name="id" value="239"/>
        </fs>
    </a>
    <node xml:id="n22">
        <link targets="r48"/>
    </node>
    <a xml:id="a-225131" label="NounChunk" ref="n22" as="anc">
        <fs>
            <f name="id" value="240"/>
        </fs>
    </a>
    <node xml:id="n23">
        <link targets="r50"/>
    </node>
    <a xml:id="a-225132" label="PRN" ref="n23" as="anc">
        <fs>
            <f name="cls" value="Person"/>
            <f name="string" value="I"/>
            <f name="gender" value="either"/>
            <f name="case" value="nominative"/>
            <f name="person" value="first"/>
            <f name="id" value="303"/>
            <f name="number" value="singular"/>
            <f name="type" value="anaphoric"/>
            <f name="matches" value="[]"/>
        </fs>
    </a>
    <a xml:id="a-225133" label="NounChunk" ref="n23" as="anc">
        <fs>
            <f name="id" value="32"/>
        </fs>
    </a>
    <node xml:id="n24">
        <link targets="r53"/>
    </node>
    <a xml:id="a-225134" label="NounChunk" ref="n24" as="anc">
        <fs>
            <f name="id" value="242"/>
        </fs>
    </a>
    <node xml:id="n25">
        <link targets="r55"/>
    </node>
    <a xml:id="a-225135" label="NounChunk" ref="n25" as="anc">
        <fs>
            <f name="id" value="243"/>
        </fs>
    </a>
    <node xml:id="n26">
        <link targets="r57"/>
    </node>
    <a xml:id="a-225136" label="PRN" ref="n26" as="anc">
        <fs>
            <f name="matches" value="[]"/>
            <f name="string" value="my"/>
            <f name="gender" value="either"/>
            <f name="case" value="possessive"/>
            <f name="person" value="first"/>
            <f name="cls" value="Person"/>
            <f name="number" value="singular"/>
            <f name="type" value="anaphoric"/>
            <f name="id" value="304"/>
        </fs>
    </a>
    <node xml:id="n27">
        <link targets="r59"/>
    </node>
    <a xml:id="a-225137" label="PRN" ref="n27" as="anc">
        <fs>
            <f name="type" value="anaphoric"/>
            <f name="matches" value="[243]"/>
            <f name="string" value="he"/>
            <f name="cls" value="Person"/>
            <f name="case" value="nominative"/>
            <f name="person" value="third"/>
            <f name="id" value="305"/>
            <f name="number" value="singular"/>
        </fs>
    </a>
    <a xml:id="a-225138" label="NounChunk" ref="n27" as="anc">
        <fs>
            <f name="id" value="34"/>
        </fs>
    </a>
    <node xml:id="n28">
        <link targets="r62"/>
    </node>
    <a xml:id="a-225139" label="NounChunk" ref="n28" as="anc">
        <fs>
            <f name="id" value="245"/>
        </fs>
    </a>
    <node xml:id="n29">
        <link targets="r64"/>
    </node>
    <a xml:id="a-225140" label="NounChunk" ref="n29" as="anc">
        <fs>
            <f name="id" value="246"/>
        </fs>
    </a>
    <node xml:id="n3">
        <link targets="r9"/>
    </node>
    <a xml:id="a-225111" label="NounChunk" ref="n3" as="anc">
        <fs>
            <f name="kind" value="emailAddress"/>
            <f name="id" value="22"/>
        </fs>
    </a>
    <node xml:id="n30">
        <link targets="r66"/>
    </node>
    <a xml:id="a-225141" label="PRN" ref="n30" as="anc">
        <fs>
            <f name="matches" value="[]"/>
            <f name="string" value="his"/>
            <f name="gender" value="male"/>
            <f name="case" value="possessive"/>
            <f name="person" value="third"/>
            <f name="cls" value="Person"/>
            <f name="number" value="singular"/>
            <f name="type" value="anaphoric"/>
            <f name="id" value="306"/>
        </fs>
    </a>
    <node xml:id="n31">
        <link targets="r68"/>
    </node>
    <a xml:id="a-225142" label="NounChunk" ref="n31" as="anc">
        <fs>
            <f name="id" value="36"/>
        </fs>
    </a>
    <a xml:id="a-225143" label="PRN" ref="n31" as="anc">
        <fs>
            <f name="cls" value="Person"/>
            <f name="string" value="he"/>
            <f name="gender" value="male"/>
            <f name="case" value="nominative"/>
            <f name="person" value="third"/>
            <f name="id" value="307"/>
            <f name="number" value="singular"/>
            <f name="type" value="anaphoric"/>
            <f name="matches" value="[243, 305]"/>
        </fs>
    </a>
    <node xml:id="n32">
        <link targets="r71"/>
    </node>
    <a xml:id="a-225144" label="NounChunk" ref="n32" as="anc">
        <fs>
            <f name="id" value="248"/>
        </fs>
    </a>
    <node xml:id="n33">
        <link targets="r73"/>
    </node>
    <a xml:id="a-225145" label="NounChunk" ref="n33" as="anc">
        <fs>
            <f name="id" value="45"/>
        </fs>
    </a>
    <a xml:id="a-225146" label="Person" ref="n33" as="anc">
        <fs>
            <f name="person" value="third"/>
            <f name="case" value="nominative"/>
            <f name="number" value="singular"/>
            <f name="corefText" value="I"/>
            <f name="id" value="539"/>
            <f name="gender" value="female"/>
        </fs>
    </a>
    <node xml:id="n34">
        <link targets="r76"/>
    </node>
    <a xml:id="a-225147" label="Location" ref="n34" as="anc">
        <fs>
            <f name="id" value="274"/>
            <f name="person" value="third"/>
            <f name="case" value="nominative"/>
            <f name="number" value="singular"/>
            <f name="locType" value="city"/>
        </fs>
    </a>
    <a xml:id="a-225148" label="NounChunk" ref="n34" as="anc">
        <fs>
            <f name="id" value="44"/>
        </fs>
    </a>
    <node xml:id="n35">
        <link targets="r79"/>
    </node>
    <a xml:id="a-225149" label="NounChunk" ref="n35" as="anc">
        <fs>
            <f name="id" value="253"/>
        </fs>
    </a>
    <node xml:id="n36">
        <link targets="r81"/>
    </node>
    <a xml:id="a-225150" label="PRN" ref="n36" as="anc">
        <fs>
            <f name="cls" value="Person"/>
            <f name="string" value="I"/>
            <f name="gender" value="either"/>
            <f name="case" value="nominative"/>
            <f name="person" value="first"/>
            <f name="id" value="308"/>
            <f name="number" value="singular"/>
            <f name="type" value="anaphoric"/>
            <f name="matches" value="[]"/>
        </fs>
    </a>
    <a xml:id="a-225151" label="NounChunk" ref="n36" as="anc">
        <fs>
            <f name="id" value="37"/>
        </fs>
    </a>
    <node xml:id="n37">
        <link targets="r84"/>
    </node>
    <a xml:id="a-225152" label="NounChunk" ref="n37" as="anc">
        <fs>
            <f name="id" value="255"/>
        </fs>
    </a>
    <node xml:id="n38">
        <link targets="r86"/>
    </node>
    <a xml:id="a-225153" label="PRN" ref="n38" as="anc">
        <fs>
            <f name="matches" value="[]"/>
            <f name="string" value="I"/>
            <f name="gender" value="either"/>
            <f name="case" value="nominative"/>
            <f name="person" value="first"/>
            <f name="cls" value="Person"/>
            <f name="number" value="singular"/>
            <f name="type" value="anaphoric"/>
            <f name="id" value="309"/>
        </fs>
    </a>
    <a xml:id="a-225154" label="NounChunk" ref="n38" as="anc">
        <fs>
            <f name="id" value="38"/>
        </fs>
    </a>
    <node xml:id="n39">
        <link targets="r89"/>
    </node>
    <a xml:id="a-225155" label="NounChunk" ref="n39" as="anc">
        <fs>
            <f name="id" value="257"/>
        </fs>
    </a>
    <node xml:id="n4">
        <link targets="r11"/>
    </node>
    <a xml:id="a-225112" label="NounChunk" ref="n4" as="anc">
        <fs>
            <f name="kind" value="emailAddress"/>
            <f name="id" value="23"/>
        </fs>
    </a>
    <node xml:id="n40">
        <link targets="r91"/>
    </node>
    <a xml:id="a-225156" label="NounChunk" ref="n40" as="anc">
        <fs>
            <f name="id" value="39"/>
        </fs>
    </a>
    <a xml:id="a-225157" label="PRN" ref="n40" as="anc">
        <fs>
            <f name="cls" value="Person"/>
            <f name="string" value="I"/>
            <f name="gender" value="either"/>
            <f name="case" value="nominative"/>
            <f name="person" value="first"/>
            <f name="id" value="310"/>
            <f name="number" value="singular"/>
            <f name="type" value="anaphoric"/>
            <f name="matches" value="[]"/>
        </fs>
    </a>
    <node xml:id="n41">
        <link targets="r94"/>
    </node>
    <a xml:id="a-225158" label="NounChunk" ref="n41" as="anc">
        <fs>
            <f name="id" value="259"/>
        </fs>
    </a>
    <node xml:id="n42">
        <link targets="r96"/>
    </node>
    <a xml:id="a-225159" label="NounChunk" ref="n42" as="anc">
        <fs>
            <f name="id" value="260"/>
        </fs>
    </a>
    <node xml:id="n43">
        <link targets="r98"/>
    </node>
    <a xml:id="a-225160" label="NounChunk" ref="n43" as="anc">
        <fs>
            <f name="id" value="43"/>
        </fs>
    </a>
    <a xml:id="a-225161" label="PRN" ref="n43" as="anc">
        <fs>
            <f name="matches" value="[]"/>
            <f name="string" value="I"/>
            <f name="gender" value="either"/>
            <f name="case" value="nominative"/>
            <f name="person" value="first"/>
            <f name="cls" value="Person"/>
            <f name="number" value="singular"/>
            <f name="type" value="anaphoric"/>
            <f name="id" value="311"/>
        </fs>
    </a>
    <node xml:id="n44">
        <link targets="r101"/>
    </node>
    <a xml:id="a-225162" label="NounChunk" ref="n44" as="anc">
        <fs>
            <f name="id" value="262"/>
        </fs>
    </a>
    <node xml:id="n45">
        <link targets="r103"/>
    </node>
    <a xml:id="a-225163" label="NounChunk" ref="n45" as="anc">
        <fs>
            <f name="id" value="263"/>
        </fs>
    </a>
    <node xml:id="n46">
        <link targets="r105"/>
    </node>
    <a xml:id="a-225164" label="Date" ref="n46" as="anc">
        <fs>
            <f name="kind" value="duration"/>
            <f name="id" value="33264"/>
        </fs>
    </a>
    <a xml:id="a-225165" label="NounChunk" ref="n46" as="anc">
        <fs>
            <f name="id" value="264"/>
        </fs>
    </a>
    <node xml:id="n47">
        <link targets="r108"/>
    </node>
    <a xml:id="a-225166" label="NounChunk" ref="n47" as="anc">
        <fs>
            <f name="id" value="42"/>
        </fs>
    </a>
    <a xml:id="a-225167" label="PRN" ref="n47" as="anc">
        <fs>
            <f name="matches" value="[]"/>
            <f name="string" value="I"/>
            <f name="gender" value="either"/>
            <f name="case" value="nominative"/>
            <f name="person" value="first"/>
            <f name="cls" value="Person"/>
            <f name="number" value="singular"/>
            <f name="type" value="anaphoric"/>
            <f name="id" value="312"/>
        </fs>
    </a>
    <node xml:id="n48">
        <link targets="r111"/>
    </node>
    <a xml:id="a-225168" label="NounChunk" ref="n48" as="anc">
        <fs>
            <f name="id" value="266"/>
        </fs>
    </a>
    <node xml:id="n49">
        <link targets="r113"/>
    </node>
    <a xml:id="a-225169" label="NounChunk" ref="n49" as="anc">
        <fs>
            <f name="id" value="40"/>
        </fs>
    </a>
    <a xml:id="a-225170" label="Person" ref="n49" as="anc">
        <fs>
            <f name="gender" value="male"/>
            <f name="isLast" value="true"/>
            <f name="number" value="singular"/>
            <f name="case" value="nominative"/>
            <f name="person" value="third"/>
            <f name="id" value="275"/>
        </fs>
    </a>
    <node xml:id="n5">
        <link targets="r13"/>
    </node>
    <a xml:id="a-225113" label="NounChunk" ref="n5" as="anc">
        <fs>
            <f name="id" value="223"/>
        </fs>
    </a>
    <node xml:id="n50">
        <link targets="r116"/>
    </node>
    <a xml:id="a-225171" label="Location" ref="n50" as="anc">
        <fs>
            <f name="locType" value="city"/>
            <f name="person" value="third"/>
            <f name="case" value="nominative"/>
            <f name="number" value="singular"/>
            <f name="id" value="276"/>
        </fs>
    </a>
    <a xml:id="a-225172" label="NounChunk" ref="n50" as="anc">
        <fs>
            <f name="id" value="41"/>
        </fs>
    </a>
    <node xml:id="n51">
        <link targets="r119"/>
    </node>
    <a xml:id="a-225173" label="NounChunk" ref="n51" as="anc">
        <fs>
            <f name="id" value="269"/>
        </fs>
    </a>
    <node xml:id="n52">
        <link targets="r121"/>
    </node>
    <a xml:id="a-225174" label="NounChunk" ref="n52" as="anc">
        <fs>
            <f name="id" value="270"/>
        </fs>
    </a>
    <node xml:id="n53">
        <link targets="r123"/>
    </node>
    <a xml:id="a-225175" label="NounChunk" ref="n53" as="anc">
        <fs>
            <f name="kind" value="urlAddress"/>
            <f name="id" value="26"/>
        </fs>
    </a>
    <node xml:id="n6">
        <link targets="r15"/>
    </node>
    <a xml:id="a-225114" label="NounChunk" ref="n6" as="anc">
        <fs>
            <f name="id" value="224"/>
        </fs>
    </a>
    <node xml:id="n7">
        <link targets="r17"/>
    </node>
    <a xml:id="a-225115" label="NounChunk" ref="n7" as="anc">
        <fs>
            <f name="id" value="225"/>
        </fs>
    </a>
    <node xml:id="n8">
        <link targets="r19"/>
    </node>
    <a xml:id="a-225116" label="NounChunk" ref="n8" as="anc">
        <fs>
            <f name="id" value="226"/>
        </fs>
    </a>
    <node xml:id="n9">
        <link targets="r21"/>
    </node>
    <a xml:id="a-225117" label="NounChunk" ref="n9" as="anc">
        <fs>
            <f name="id" value="227"/>
            <f name="matches" value="[259]"/>
        </fs>
    </a>
</graph>
